lagrange_interpolation/__init__.py
lagrange_interpolation/module_func.py
lagrange_interpolation_genii_evgenii-0.2.1.dist-info/LICENSE
lagrange_interpolation_genii_evgenii-0.2.1.dist-info/METADATA
lagrange_interpolation_genii_evgenii-0.2.1.dist-info/WHEEL
lagrange_interpolation_genii_evgenii-0.2.1.dist-info/top_level.txt
lagrange_interpolation_genii_evgenii-0.2.1.dist-info/RECORD
