Metadata-Version: 2.1
Name: lagrange_interpolation_genii_evgenii
Version: 0.2.1
Summary: Lagrange interpolation package
Home-page: https://www.instagram.com/eug_borodin/
Author: Borodin Evgenii
Author-email: j.borodin1@gmail.com
License: UNKNOWN
Platform: UNKNOWN
Classifier: Programming Language :: Python :: 3
Classifier: License :: OSI Approved :: MIT License
Classifier: Operating System :: OS Independent
Requires-Python: >=3
License-File: LICENSE
